altena/__init__.py
altena/encoder.py
altena/entity_embedding.py
altena/evaluator.py
velvet/__init__.py
velvet/encoder.py
velvet/entity_embedding.py
velvet/evaluator.py
altena-0.0.1.dist-info/METADATA
altena-0.0.1.dist-info/WHEEL
altena-0.0.1.dist-info/top_level.txt
altena-0.0.1.dist-info/RECORD
